tox_demo/hello_world.py
tox_demo-0.2.0.dist-info/WHEEL
tox_demo-0.2.0.dist-info/METADATA
tox_demo-0.2.0.dist-info/RECORD
